{
  "category": "blogs",
  "contentKind": "article",
  "entryId": "why-is-sso-important--18",
  "legacy": {
    "extraSegments": [],
    "legacyId": "18",
    "sourceCategory": "blog",
    "sourceGroupPath": "documentation/blog/18/why-is-sso-important",
    "sourceUrl": "/features/documentation/blog/18/why-is-sso-important"
  },
  "locales": {
    "en": {
      "assetRefs": [
        {
          "exists": true,
          "sourcePath": "public/blog/b-thumb-18.webp",
          "webPath": "/blog/b-thumb-18.webp"
        },
        {
          "exists": true,
          "sourcePath": "public/blog/blog18-image-1.webp",
          "webPath": "/blog/blog18-image-1.webp"
        }
      ],
      "bodyPath": "src/content/managed/documentation/blogs/why-is-sso-important--18/en.mdx",
      "contentKind": "article",
      "description": "Understand why Single Sign-On (SSO) is crucial for enhancing user experience, streamlining access, and improving security across multiple platforms. See the benefits today!",
      "hideOgImage": false,
      "hideTableOfContents": false,
      "keywords": [
        "Single Sign-On",
        "SSO benefits",
        "SSO security",
        "SSO authentication"
      ],
      "layout": "Article",
      "ogImage": "/blog/b-thumb-18.webp",
      "rawFrontmatter": "layout: \"Article\"\ncategory: \"blog\"\ntitle: \"Why is SSO important?\"\ndescription: \"Understand why Single Sign-On (SSO) is crucial for enhancing user experience, streamlining access, and improving security across multiple platforms. See the benefits today!\"\ndate: \"2025-02-04\"\nauthor: \"jk\"\nogImage: \"public/blog/b-thumb-18.webp\"\nkeywords: [\"Single Sign-On\", \"SSO benefits\", \"SSO security\", \"SSO authentication\"]\nrelatedPosts:\n  - \"/features/documentation/blog/17/privileged-access-management-pam\"\n  - \"/features/documentation/blog/16/healthcare-data-security\"\n  - \"/features/documentation/blog/15/zero-trust-security\"",
      "relatedPosts": [
        "/features/documentation/blog/17/privileged-access-management-pam",
        "/features/documentation/blog/16/healthcare-data-security",
        "/features/documentation/blog/15/zero-trust-security"
      ],
      "sourcePath": "documentation/blog/18/why-is-sso-important/en/content.mdx",
      "title": "Why is SSO important?",
      "frontmatter": {
        "layout": "Article",
        "category": "blog",
        "title": "Why is SSO important?",
        "description": "Understand why Single Sign-On (SSO) is crucial for enhancing user experience, streamlining access, and improving security across multiple platforms. See the benefits today!",
        "date": "2025-02-04",
        "author": "jk",
        "ogImage": "public/blog/b-thumb-18.webp",
        "keywords": [
          "Single Sign-On",
          "SSO benefits",
          "SSO security",
          "SSO authentication"
        ],
        "relatedPosts": [
          "/features/documentation/blog/17/privileged-access-management-pam",
          "/features/documentation/blog/16/healthcare-data-security",
          "/features/documentation/blog/15/zero-trust-security"
        ]
      }
    },
    "ko": {
      "assetRefs": [
        {
          "exists": true,
          "sourcePath": "public/blog/b-thumb-18.webp",
          "webPath": "/blog/b-thumb-18.webp"
        },
        {
          "exists": true,
          "sourcePath": "public/blog/blog18-image-1.webp",
          "webPath": "/blog/blog18-image-1.webp"
        }
      ],
      "bodyPath": "src/content/managed/documentation/blogs/why-is-sso-important--18/ko.mdx",
      "contentKind": "article",
      "description": "SSO(Single Sign-On)가 사용자 경험을 향상시키고, 여러 플랫폼에 대한 접근을 간소화하며, 보안을 어떻게 강화할 수 있는지 지금 그 방법을 알아보세요!",
      "hideOgImage": false,
      "hideTableOfContents": false,
      "keywords": [
        "싱글 사인온",
        "SSO의 장점",
        "SSO 보안",
        "SSO 인증"
      ],
      "layout": "Article",
      "ogImage": "/blog/b-thumb-18.webp",
      "rawFrontmatter": "layout: \"Article\"\ncategory: \"blog\"\ntitle: \"SSO, 왜 그렇게 중요할까요?\"\ndescription: \"SSO(Single Sign-On)가 사용자 경험을 향상시키고, 여러 플랫폼에 대한 접근을 간소화하며, 보안을 어떻게 강화할 수 있는지 지금 그 방법을 알아보세요!\"\ndate: \"2025-02-04\"\nauthor: \"jk\"\nogImage: \"public/blog/b-thumb-18.webp\"\nkeywords: [\"싱글 사인온\", \"SSO의 장점\", \"SSO 보안\", \"SSO 인증\"]\nrelatedPosts:\n  - \"/features/documentation/blog/19/optimize-ec2-costs\"\n  - \"/features/documentation/blog/1/agentless-philosophy\"\n  - \"/features/documentation/blog/4/multi-cloud-kubernetes-access-control\"",
      "relatedPosts": [
        "/features/documentation/blog/19/optimize-ec2-costs",
        "/features/documentation/blog/1/agentless-philosophy",
        "/features/documentation/blog/4/multi-cloud-kubernetes-access-control"
      ],
      "sourcePath": "documentation/blog/18/why-is-sso-important/ko/content.mdx",
      "title": "SSO, 왜 그렇게 중요할까요?",
      "frontmatter": {
        "layout": "Article",
        "category": "blog",
        "title": "SSO, 왜 그렇게 중요할까요?",
        "description": "SSO(Single Sign-On)가 사용자 경험을 향상시키고, 여러 플랫폼에 대한 접근을 간소화하며, 보안을 어떻게 강화할 수 있는지 지금 그 방법을 알아보세요!",
        "date": "2025-02-04",
        "author": "jk",
        "ogImage": "public/blog/b-thumb-18.webp",
        "keywords": [
          "싱글 사인온",
          "SSO의 장점",
          "SSO 보안",
          "SSO 인증"
        ],
        "relatedPosts": [
          "/features/documentation/blog/19/optimize-ec2-costs",
          "/features/documentation/blog/1/agentless-philosophy",
          "/features/documentation/blog/4/multi-cloud-kubernetes-access-control"
        ]
      }
    },
    "ja": {
      "assetRefs": [
        {
          "exists": true,
          "sourcePath": "public/blog/b-thumb-18.webp",
          "webPath": "/blog/b-thumb-18.webp"
        },
        {
          "exists": true,
          "sourcePath": "public/blog/blog18-image-1.webp",
          "webPath": "/blog/blog18-image-1.webp"
        }
      ],
      "bodyPath": "src/content/managed/documentation/blogs/why-is-sso-important--18/ja.mdx",
      "contentKind": "article",
      "description": "SSO（シングルサインオン）がどのようにユーザー体験を向上させ、複数のプラットフォームへのアクセスを簡素化し、セキュリティを強化する方法を今すぐ確認してください！",
      "hideOgImage": false,
      "hideTableOfContents": false,
      "keywords": [
        "シングルサインオン",
        "SSOの利点",
        "SSOセキュリティ",
        "SSO認証"
      ],
      "layout": "Article",
      "ogImage": "/blog/b-thumb-18.webp",
      "rawFrontmatter": "layout: \"Article\"\ncategory: \"blog\"\ntitle: \"SSOはなぜ重要なのか？\"\ndescription: \"SSO（シングルサインオン）がどのようにユーザー体験を向上させ、複数のプラットフォームへのアクセスを簡素化し、セキュリティを強化する方法を今すぐ確認してください！\"\ndate: \"2025-02-04\"\nauthor: \"jk\"\nogImage: \"public/blog/b-thumb-18.webp\"\nkeywords: [\"シングルサインオン\", \"SSOの利点\", \"SSOセキュリティ\", \"SSO認証\"]\nrelatedPosts:\n  - \"/features/documentation/blog/19/optimize-ec2-costs\"\n  - \"/features/documentation/blog/10/customer-centric-tpm-life\"\n  - \"/features/documentation/blog/2/querypie-cracking-global-markets\"",
      "relatedPosts": [
        "/features/documentation/blog/19/optimize-ec2-costs",
        "/features/documentation/blog/10/customer-centric-tpm-life",
        "/features/documentation/blog/2/querypie-cracking-global-markets"
      ],
      "sourcePath": "documentation/blog/18/why-is-sso-important/ja/content.mdx",
      "title": "SSOはなぜ重要なのか？",
      "frontmatter": {
        "layout": "Article",
        "category": "blog",
        "title": "SSOはなぜ重要なのか？",
        "description": "SSO（シングルサインオン）がどのようにユーザー体験を向上させ、複数のプラットフォームへのアクセスを簡素化し、セキュリティを強化する方法を今すぐ確認してください！",
        "date": "2025-02-04",
        "author": "jk",
        "ogImage": "public/blog/b-thumb-18.webp",
        "keywords": [
          "シングルサインオン",
          "SSOの利点",
          "SSOセキュリティ",
          "SSO認証"
        ],
        "relatedPosts": [
          "/features/documentation/blog/19/optimize-ec2-costs",
          "/features/documentation/blog/10/customer-centric-tpm-life",
          "/features/documentation/blog/2/querypie-cracking-global-markets"
        ]
      }
    }
  },
  "section": "documentation",
  "slug": "why-is-sso-important"
}
